erniebot/__init__.py
erniebot/__main__.py
erniebot/api_types.py
erniebot/auth.py
erniebot/cli.py
erniebot/config.py
erniebot/constants.py
erniebot/errors.py
erniebot/http_client.py
erniebot/intro.py
erniebot/py.typed
erniebot/response.py
erniebot/types.py
erniebot/version.py
erniebot/backends/__init__.py
erniebot/backends/aistudio.py
erniebot/backends/base.py
erniebot/backends/bce.py
erniebot/backends/custom.py
erniebot/resources/__init__.py
erniebot/resources/chat_completion.py
erniebot/resources/chat_completion_with_plugins.py
erniebot/resources/embedding.py
erniebot/resources/fine_tuning.py
erniebot/resources/image.py
erniebot/resources/resource.py
erniebot/resources/abc/__init__.py
erniebot/resources/abc/cancellable.py
erniebot/resources/abc/creatable.py
erniebot/resources/abc/protocol.py
erniebot/resources/abc/queryable.py
erniebot/utils/__init__.py
erniebot/utils/bos.py
erniebot/utils/logging.py
erniebot/utils/misc.py
erniebot/utils/token_helper.py
erniebot/utils/url.py
erniebot-0.5.9.dist-info/LICENSE
erniebot-0.5.9.dist-info/METADATA
erniebot-0.5.9.dist-info/WHEEL
erniebot-0.5.9.dist-info/entry_points.txt
erniebot-0.5.9.dist-info/top_level.txt
erniebot-0.5.9.dist-info/RECORD
