Metadata-Version: 2.1
Name: erniebot
Version: 0.5.9
Summary: Python library for the ERNIE Bot
Classifier: Programming Language :: Python
Requires-Python: >=3.8
License-File: LICENSE
Requires-Dist: aiohttp
Requires-Dist: bce-python-sdk
Requires-Dist: colorlog
Requires-Dist: jsonschema >=4.19
Requires-Dist: requests >=2.20
Requires-Dist: tenacity
Requires-Dist: typing-extensions >=4.8.0
Provides-Extra: docs
Requires-Dist: commonmark ; extra == 'docs'
Requires-Dist: mkdocs ; extra == 'docs'
Requires-Dist: mkdocs-material ; extra == 'docs'
Requires-Dist: mkdocs-material-extensions ; extra == 'docs'
Requires-Dist: pymdown-extensions ; extra == 'docs'
Requires-Dist: recommonmark ; extra == 'docs'
Requires-Dist: Sphinx ; extra == 'docs'
Requires-Dist: sphinx-markdown-tables ; extra == 'docs'
